{
    "name_ru": "Сотворение магического руля",
    "name_en": "Creating spelljamming helm",
    "level": "5",
    "school": "преобразование",
    "time": "1 действие",
    "distans": "Касание",
    "components": "В, С, М (кристаллический жезл стоимостью как минимум 5000 зм, расходуемый заклинанием)",
    "time_doing": "Мгновенная",
    "class": "волшебник, изобретатель",
    "text": "Удерживая жезл, используемый для накладывания заклинания, вы касаетесь незанятого сиденья не более Большого размера. Жезл исчезает, а сиденье превращается в магический руль [spelljamming helm]."
}