{
    "name_ru": "Заточение",
    "name_en": "Imprisonment",
    "level": "9",
    "school": "ограждение",
    "time": "1 минута",
    "distans": "30 футов",
    "components": "В, С, М (рисунок или резная статуэтка, изображающая цель, и особый компонент, зависящий от выбранной версии заклинания, стоящий как минимум 500 зм за каждую Кость Хитов цели)",
    "time_doing": "Пока не рассеяно",
    "class": "волшебник, колдун",
    "text": "Вы создаёте магические оковы, удерживающие существо, видимое вами в пределах дистанции. Цель должна преуспеть в спасброске Мудрости, иначе она станет скованной заклинанием; при успехе цель получает иммунитет к этому заклинанию, если вы будете накладывать его повторно. Находясь под действием этого заклинания, существо не обязано дышать, есть и пить, и оно не стареет. Заклинания школы Прорицания не могут найти или почувствовать цель.\nПри накладывании этого заклинания вы выбираете один из следующих видов заточения:\nЗахоронение. Цель становится заточённой глубоко под землёй в сфере из магической силы, достаточно большой, чтобы цель могла в ней поместиться. Ничто не может проникнуть сквозь эту сферу, и никакие существа не могут при помощи телепортации или путешествий между планами проникнуть внутрь или наружу.\nОсобым компонентом для этой версии заклинания является небольшая мифриловая сфера.\nМиниатюризация. Цель уменьшается до высоты 1 дюйм (2,5 сантиметра), и становится заточённой в драгоценном камне или подобном предмете. Свет проходит через камень как обычно (что позволяет цели видеть, а другим существам видеть её), но больше сквозь него ничто не проходит, даже за счёт телепортации и планарных путешествий. Пока заклинание активно, этот камень нельзя ни разрезать, ни сломать.\nОсобым компонентом для этой версии заклинания является большой прозрачный драгоценный камень, такой как корунд, алмаз или рубин.\nОграждённая тюрьма. Заклинание переносит цель в крохотный демиплан, защищённый от телепортации и планарных путешествий. Это может быть лабиринт, клетка, башня или другое подобное укреплённое строение или местность.\nОсобым компонентом для этой версии заклинания является миниатюрная копия тюрьмы, изготовленная из нефрита.\nОцепенение. Цель засыпает, и её нельзя разбудить. Особым компонентом для этой версии заклинания являются редкие снотворные травы.\nСковывание. Цель удерживают на месте толстые цепи, крепко связанные с землёй. Цель опутана, пока заклинание активно, и в это время она не может перемещаться и каким-либо образом быть перемещенной.\nОсобым компонентом для этой версии заклинания является тонкая цепочка из драгоценного металла.\nОкончание заклинания. Во время накладывания этого заклинания, какую бы версию вы не выбрали, вы можете указать условие, оканчивающее заклинание и отпускающее цель. Условие может быть простым или замысловатым, но Мастер должен признать условие разумным и вероятным. Условия могут основываться на имени существа, его личности или его божестве, но во всём остальном должны полагаться на обозримые действия или качества, и не должны основываться на таких неосязаемых факторах как уровень, класс или хиты.\nЗаклинание рассеивание магии [dispel magic] может окончить это заклинание, только если будет наложено ячейкой 9-го уровня, нацеливаясь либо на тюрьму, либо на особый компонент, использовавшийся для её создания.\nВы можете использовать конкретный особый компонент для создания только одной тюрьмы одновременно. Если вы наложите это заклинание ещё раз, используя тот же компонент, предыдущая цель тут же освобождается."
}