{
    "name_ru": "Облачение камня",
    "name_en": "Investiture of stone",
    "level": "6",
    "school": "преобразование",
    "time": "1 действие",
    "distans": "На себя",
    "components": "В, С",
    "time_doing": "Концентрация, вплоть до 10 минут",
    "class": "волшебник, друид, колдун, чародей",
    "text": "Вы можете передвигаться по труднопроходимой местности, состоящей из земли или камня, не тратя дополнительное перемещение. Вы можете проходить сквозь твёрдую землю или камень так, словно это воздух, не разрушая их, однако не можете закончить там перемещение. Если вы заканчиваете перемещение, находясь внутри земли или камня, вас выталкивает в ближайшее свободное пространство, заклинание заканчивается, и вы становитесь ошеломлённым до конца своего следующего хода."
}